{"title":"Combined feed","url":"https://MOVIECORD.github.io/entertain/all.xml","elements":[{"title":"월세는 오르고 손님은 없고... 현실 앞에 흔들린 우정 (다음 연예 ─ 뉴스 ─ 영화)","contents":"[김성호 기자] 제25회 전주국제영화제, 특별상영 섹션 가운데는 '지역 독립영화 쇼케이스'가 있다. 전국 각지, 지역에서 기획되고 만들어진 영화들을 전주를 찾은 영화팬 앞에서 소개하는 섹션이다. 이미 다른 영화제에서 발표된 바 있는 작품들로, 전주영화제에서 경쟁이며 다른 섹션에 삽입될 자격을 갖지 못한 경우가 대부분이다. 단 몇 시간이면 서울에서 부산까지,","link":"https://v.daum.net/v/20240522101501697","retrieved":1716340541652},{"title":"'설계자' 강동원이 전부가 아니야..신선한 소재→웰메이드 볼거리 '가득' (다음 연예 ─ 뉴스 ─ 영화)","contents":"[스포츠조선 조지영 기자] 범죄 영화 '설계자'(이요섭 감독, 영화사 집 제작)가 개봉에 앞서 관객들을 사로잡을 매력적인 컨피덴셜 세 가지를 공개했다. 첫 번째 컨피덴셜은 계획된 살인을 우연한 사고로 조작하는 신선한 소재다. 이름, 나이, 출신 그 어떤 기록도 세상에 남아있지 않은 설계자 영일(강동원)은 타겟을 제거하는 데 유리한 신분을 활용","link":"https://v.daum.net/v/20240522100855435","retrieved":1716340541653},{"title":"\"설레고 긴장...현장 궁금해요\" 김아영, '히트 히트 히트'로 스크린 데뷔 (다음 연예 ─ 뉴스 ─ 영화)","contents":"(MHN스포츠 장민수 기자) 배우 김아영이 '히트 히트 히트'를 통해 스크린 데뷔를 갖는다. 22일 소속사 AIMC 측은 \"김아영이 영화 '히트 히트 히트'(가제)에 캐스팅\"됐다고 밝혔다. '히트 히트 히트'는 힙합씬의 주인공을 꿈꾸는 힙찌리 원이가 자신의 곡을 훔쳐간 범인을 쫓으며 벌어지는 지뢰 같은 사건들의 여정을 그린 힙합 코미디 추격극이","link":"https://v.daum.net/v/20240522100504276","retrieved":1716340541654},{"title":"정해인 \"칸영화제 참석 계기로 변화? 없을 것\" 확언한 이유 (다음 연예 ─ 뉴스 ─ 영화)","contents":"(칸, 서울=뉴스1) 이준성 장아름 기자 = 배우 정해인이 칸 국제영화제 참석 전후로 크게 달라지는 점은 없을 것이라고 확언했다. 정해인은 지난 21일(현지시간) 프랑스 남부 칸에서 개최된 제77회 칸 국제영화제에서 뉴스1과 만나 이번 칸 국제영화제 참석 전후로 달라진 점에 대해 묻는 질문에 \"칸은 칸\"이라며 \"똑같다\"고 답했다. 이어 그는 \"돌아가서","link":"https://v.daum.net/v/20240522100255167","retrieved":1716340541655},{"title":"조진웅·염정아→허광한 출연 ‘노 웨이 아웃’, 7월 첫 공개 (다음 연예 ─ 뉴스 ─ 영화)","contents":"‘노 웨이 아웃’이 화려한 캐스팅 라인업으로 공개 전부터 기대를 자아내고 있다. 22일 STUDIO X+U는 조진웅, 유재명, 김무열, 염정아, 성유빈, 허광한, 이광수, 김성철 등이 출연하는 ‘노 웨이 아웃: 더 룰렛’(이하 ‘노 웨이 아웃’)이 오는 7월 공개된다고 밝혔다. ‘노 웨이 아웃’은 희대의 흉악범 김국호의 목숨에 200억 원의 공개살인청부","link":"https://v.daum.net/v/20240522095725863","retrieved":1716340541656},{"title":"길게 봐서 더 좋다, ‘신인 삼촌’ 송강호 (다음 연예 ─ 뉴스 ─ 영화)","contents":"“사랑과 존경의 의미로 다들 그렇게 불러요. ‘삼식이 삼촌’, 제 별명이요.” 좀 느려도 괜찮다, 기다린 만큼 보상 받았을 수 있으니. 송강호의 데뷔 35년 만 ‘드라마 데뷔작’, 이것 만으로 볼 이유는 충분, 어느 새 납득 당한다. 초반부 다소 쉽지 않은 장벽을 넘으니, 본격적인 신세계가 펼쳐진다. 묵직한듯 날렵하고, 빈틈 없이 촘촘한, 갈수록 매혹적인","link":"https://v.daum.net/v/20240522095110608","retrieved":1716340541658},{"title":"탕웨이·수지·박보검→니나 파우·최무성…'원더랜드' 초호화 캐스팅 \"원더풀\" (다음 연예 ─ 뉴스 ─ 영화)","contents":"[스포티비뉴스-유은비 기자] 탕웨이, 수지, 박보검, 정유미, 최우식, 그리고 특별출연 공유까지 화려한 캐스팅으로 화제를 모으고 있는 영화 '원더랜드'에 세대와 국적을 아우르는 탄탄한 연기력의 배우들이 총출동했다. 탕웨이, 수지, 박보검, 정유미, 최우식, 특별출연 공유 등 대세 배우들이 총출동한 김태용 감독의 신작 '원더랜드'에 세대 불문, 국적 불","link":"https://v.daum.net/v/20240522094851530","retrieved":1716340541660},{"title":"정해인 \"로맨틱 이미지 떨친지 오래…'베테랑2'로 화 다 풀었다\" (다음 연예 ─ 뉴스 ─ 영화)","contents":"(칸, 서울=뉴스1) 이준성 장아름 기자 = 배우 정해인이 '베테랑2'에서의 활약을 예고했다. 정해인은 지난 21일(현지시간) 프랑스 남부 칸에서 개최된 제77회 칸 국제영화제에서 뉴스1과 만나 '베테랑2'에 대한 이야기를 나눴다. '베테랑2'는 악인은 끝까지 잡는 베테랑 서도철 형사(황정민 분)의 강력범죄수사대에 막내 박선우 형사(정해인 분)가 합류","link":"https://v.daum.net/v/20240522094654457","retrieved":1716340541661},{"title":"한한령도 문제없어…'범죄도시4', 상하이국제영화제 공식 초청 (다음 연예 ─ 뉴스 ─ 영화)","contents":"[SBS 연예뉴스 | 김지혜 기자] 영화 '범죄도시4'가 제26회 상하이국제영화제 '미드나잇 판타지' 부문에 공식 초청됐다. 한국영화 시리즈 최초 누적 관객수 4천만, 시리즈 3편 연속 트리플 천만 기록을 경신한 '범죄도시4'가 글로벌한 흥행 열풍을 이어간다. 지난 2월 베를린국제영화제 공식 초청에 이어 오는 6월 14일(금)부터 23일(일)까지 약 열흘간","link":"https://v.daum.net/v/20240522094508389","retrieved":1716340541665},{"title":"‘하이재킹’ 제작보고회, 여진구 파격 악역변신을 기대하라 (다음 연예 ─ 뉴스 ─ 영화)","contents":"22일에도 연예계 다양한 행사와 인터뷰가 독자들을 찾아간다. 이날 오전 11시 서울 용산구 CGV 용산 아이파크몰에서는 김성한 감독의 영화 ‘하이재킹’의 제작보고회가 열린다. 이 자리에는 김성한 감독과 함께 주연 배우 하정우, 여진구, 성동일, 채수빈이 참석한다. ‘하이재킹’은 1971년 대한민국을 배경으로 상공에서 여객기가 공중 납치되면서 벌어지는","link":"https://v.daum.net/v/20240522093931179","retrieved":1716340541666},{"title":"'하이재킹' 하정우→여진구, 극한의 서스펜스 담은 13종 보도스틸 공개 (다음 연예 ─ 뉴스 ─ 영화)","contents":"[스포츠투데이 서지현 기자] '하이재킹'이 극한의 서스펜스를 예고했다. 영화 '하이재킹' 측은 22일 한정된 공간 속 극한의 서스펜스를 담은 보도스틸 13종을 공개했다. '하이재킹'은 1971년 대한민국 상공, 여객기가 공중 납치되면서 벌어지는 극한의 상황을 담고 있다. 공개된 스틸 속엔 뛰어난 비행 실력으로 촉망받던 공군 전투기 조종사에서 여객기의 부기장","link":"https://v.daum.net/v/20240522093845123","retrieved":1716340541668},{"title":"'하이재킹' 하정우vs여진구, 납치된 여객기 극한의 서스펜스 (다음 연예 ─ 뉴스 ─ 영화)","contents":"[OSEN=하수정 기자] 여객기 공중 납치 사건, 일명 ‘하이재킹’의 위기 상황을 그려낸 영화 '하이재킹' 공중에서 여객기가 납치된 극한의 상황을 생생히 담은 보도스틸을 공개했다. 1971년 대한민국 상공, 여객기가 공중 납치되면서 벌어지는 극한의 상황을 담은 영화 '하이재킹'이 여객기가 납치된 극한의 상황과 각자의 자리에서 최선을 다한 캐릭터들의 강렬","link":"https://v.daum.net/v/20240522093650061","retrieved":1716340541669},{"title":"‘OTT 넘어 첫 스크린 데뷔’ 김아영 “작품 속 인물이 나같아” (다음 연예 ─ 뉴스 ─ 영화)","contents":"배우 김아영이 ‘히트 히트 히트’를 통해 극장가를 찾을 예정이다. 김아영이 영화 ‘히트 히트 히트’(가제)에 캐스팅돼 활약을 예고했다. 그가 출연을 확정 지은 ‘히트 히트 히트’는 힙합씬의 주인공을 꿈꾸는 힙찌리 원이가 자신의 곡을 훔쳐간 범인을 쫓으며 벌어지는 지뢰 같은 사건들의 여정을 그린 힙합 코미디 추격극이다. 김아영은 극 중 웃음을 책","link":"https://v.daum.net/v/20240522093409936","retrieved":1716340541671},{"title":"이성민X이희준, 비주얼 사납네…\"생긴 게 범죄자 몽타주\" (다음 연예 ─ 뉴스 ─ 영화)","contents":"[텐아시아=김지원 기자] '핸섬가이즈'가 멋진 동시에 참을 수 없는 웃음을 유발하는 듀오 포스터와 세계관 파괴 포스터, 1차 예고편을 공개했다.&nbsp; '핸섬가이즈'는 한 번 보면 절대 잊을 수 없는 재필과 상구가 전원생활을 꿈꾸며 새집으로 이사 온 날, 지하실에 봉인됐던 악령이 깨어나며 벌어지는 고자극 오싹 코미디. '핸섬가이즈'가 참을 수 없는 궁금증을","link":"https://v.daum.net/v/20240522093008780","retrieved":1716340541673},{"title":"아드레날린 치솟는 그녀의 질주… ‘퓨리오사 : 매드맥스 사가’ (다음 연예 ─ 뉴스 ─ 영화)","contents":"매주 영화는 개봉하고, 관객들은 영화관에 갈지 고민합니다. 정보는 쏟아지는데, 어떤 얘길 믿을지 막막한 세상에서 영화 담당 기자가 살포시 영화 큐레이션을 해드립니다. ‘그 영화 보러 가, 말아’란 고민에 시사회에서 먼저 감 잡은 기자가 ‘감’ ‘안 감’으로 답을 제안해봅니다. 잔혹한 세상의 종말에 무엇으로 맞서 싸울 수 있을까. 22일 개봉한","link":"https://v.daum.net/v/20240522092848728","retrieved":1716340541674}]}